suricat/cabs/__init__.py
suricat/cabs/suricat.yml
suricat/recipes/__init__.py
suricat/recipes/init.yml
suricat_beams_cabs-0.1.2.dist-info/LICENSE
suricat_beams_cabs-0.1.2.dist-info/METADATA
suricat_beams_cabs-0.1.2.dist-info/WHEEL
suricat_beams_cabs-0.1.2.dist-info/RECORD
