Metadata-Version: 2.3
Name: suricat-beams-cabs
Version: 0.1.2
Summary: MeerKAT primary beam model handling utilities -- Stimela cabs and recipes
License: MIT
Author: Oleg Smirnov
Author-email: osmirnov@gmail.com
Requires-Python: >=3.8,<4.0
Classifier: License :: OSI Approved :: MIT License
Classifier: Programming Language :: Python :: 3
Classifier: Programming Language :: Python :: 3.8
Classifier: Programming Language :: Python :: 3.9
Classifier: Programming Language :: Python :: 3.10
Classifier: Programming Language :: Python :: 3.11
Classifier: Programming Language :: Python :: 3.12
Classifier: Programming Language :: Python :: 3.13
Requires-Dist: stimela (>=2.0,<3.0)
